fabfile.py
fabricutils.py
fabricutils-0.2.1.dist-info/LICENSE
fabricutils-0.2.1.dist-info/METADATA
fabricutils-0.2.1.dist-info/WHEEL
fabricutils-0.2.1.dist-info/top_level.txt
fabricutils-0.2.1.dist-info/RECORD
