Metadata-Version: 2.1
Name: fabricutils
Version: 0.2.1
Summary: Fabric helper utilities
Home-page: https://github.com/makukha/fabricutils
Author: Michael Makukha
Author-email: m.makukha@gmail.com
License: MIT
Platform: UNKNOWN
Classifier: License :: OSI Approved :: MIT License
Classifier: Programming Language :: Python :: 3
Classifier: Programming Language :: Python :: 3.7
Requires-Dist: fabric (>=2.4.0)
